{"dataflow":{"dfKey":"7c860925-e15a-4228-a5c2-f5baacbd0526","name":"qctc_720_Copy","tags":null,"description":null,"definition":"{\"name\":\"qctc_720_Copy\",\"engineVariableName\":\"\",\"components\":[{\"query\":\"select * from  customers\",\"partitionOptions\":{\"partitionType\":\"\",\"name\":\"\"},\"enableTrim\":\"N\",\"easyQueryDefJson\":{\"sqlQuery\":\"\"},\"componentId\":1,\"componentName\":\"Source JDBC\",\"tableName\":\"Source_JDBC_DBCAB4_jfTP\",\"category\":\"Source\",\"componentType\":\"TestCase JDBC\",\"rank\":0,\"dataSourceName\":\"Oracle\",\"displayRows\":50,\"dependencies\":[],\"className\":\"com.datagaps.dataflow.models.JDBCComponent\",\"executionOption\":\"allparentpassorfail\",\"excludeNotification\":\"N\"},{\"query\":\"select * from customer\",\"partitionOptions\":{\"partitionType\":\"\",\"name\":\"\"},\"enableTrim\":\"N\",\"easyQueryDefJson\":{\"sqlQuery\":\"\"},\"componentId\":2,\"componentName\":\"Target JDBC\",\"tableName\":\"Target_JDBC_C1F48A_lnuK\",\"category\":\"Source\",\"componentType\":\"TestCase JDBC\",\"rank\":0,\"dataSourceName\":\"MySQL\",\"displayRows\":50,\"dependencies\":[],\"className\":\"com.datagaps.dataflow.models.JDBCComponent\",\"executionOption\":\"allparentpassorfail\",\"excludeNotification\":\"N\"},{\"sourceDataFrame\":\"Source_JDBC_DBCAB4_jfTP\",\"targetDataFrame\":\"Target_JDBC_C1F48A_lnuK\",\"mapping\":[{\"sourceColumn\":\"CUST_EMAIL\",\"sourceType\":\"VARCHAR\",\"targetColumn\":\"EMAIL\",\"targetType\":\"VARCHAR\",\"unique\":\"N\",\"sourceDataFormat\":\"\",\"targetDataFormat\":\"\",\"sourceTypeChange\":\"N\",\"targetTypeChange\":\"N\",\"originalSourceType\":\"VARCHAR\",\"orginalTargetType\":\"VARCHAR\"},{\"sourceColumn\":\"CUST_LAST_NAME\",\"sourceType\":\"VARCHAR\",\"targetColumn\":\"LAST_NAME\",\"targetType\":\"VARCHAR\",\"unique\":\"N\",\"sourceDataFormat\":\"\",\"targetDataFormat\":\"\",\"sourceTypeChange\":\"N\",\"targetTypeChange\":\"N\",\"originalSourceType\":\"VARCHAR\",\"orginalTargetType\":\"VARCHAR\"},{\"sourceColumn\":\"CUST_FIRST_NAME\",\"sourceType\":\"VARCHAR\",\"targetColumn\":\"FIRST_NAME\",\"targetType\":\"VARCHAR\",\"unique\":\"N\",\"sourceDataFormat\":\"\",\"targetDataFormat\":\"\",\"sourceTypeChange\":\"N\",\"targetTypeChange\":\"N\",\"originalSourceType\":\"VARCHAR\",\"orginalTargetType\":\"VARCHAR\"},{\"sourceColumn\":\"CUST_ID\",\"sourceType\":\"float\",\"targetColumn\":\"CUSTOMER_ID\",\"targetType\":\"float\",\"unique\":\"Y\",\"sourceDataFormat\":\"\",\"targetDataFormat\":\"\",\"sourceTypeChange\":\"Y\",\"targetTypeChange\":\"Y\",\"originalSourceType\":\"NUMBER\",\"orginalTargetType\":\"NUMBER\"}],\"onlyInA\":\"Y\",\"onlyInB\":\"Y\",\"difference\":\"Y\",\"enableTrim\":\"N\",\"replaceNull\":\"N\",\"autoDataTypeConversion\":\"Y\",\"columnDifferencesCount\":\"N\",\"ignoreCase\":\"N\",\"hasDuplicates\":\"N\",\"subDataFrames\":[{\"subDataFrameName\":\"_Matched\",\"type\":\"Matched\"},{\"subDataFrameName\":\"_Source_Duplicate\",\"type\":\"Duplicates In A\"},{\"subDataFrameName\":\"_Target_Duplicate\",\"type\":\"Duplicates In B\"},{\"subDataFrameName\":\"_Difference\",\"type\":\"Difference\"},{\"subDataFrameName\":\"_OnlySource\",\"type\":\"Only In A\"},{\"subDataFrameName\":\"_OnlyTarget\",\"type\":\"Only In B\"}],\"onlyInAThresholdUnit\":\"number\",\"onlyInAThreshold\":0.0,\"onlyInBThresholdUnit\":\"number\",\"onlyInBThreshold\":0.0,\"differencesSourceThresholdUnit\":\"number\",\"differencesSourceThreshold\":0.0,\"differencesTargetThresholdUnit\":\"number\",\"differencesTargetThreshold\":0.0,\"componentId\":3,\"componentName\":\"Data Compare\",\"tableName\":\"Data_Compare_831769_zquv\",\"category\":\"Data Reconciliation\",\"componentType\":\"TestCase DataCompare\",\"rank\":0,\"dataSourceName\":\"\",\"displayRows\":50,\"dependencies\":[1,2],\"options\":{},\"className\":\"com.datagaps.dataflow.models.DataCompareComponent\",\"executionOption\":\"allparentpassorfail\",\"excludeNotification\":\"N\"}],\"isDeleteWorkSchemaTable\":\"N\"}","parameters":"[{\"type\":\"static\",\"name\":\"limit_rows\",\"defValueInInteractiveMode\":\"limit 10\",\"defValueInBatchMode\":\"limit 1000\"}]","version":3,"maxComponentId":3,"livyOptions":null,"isDeleted":"N","userName":null,"type":"querycomparetestcase","environmentName":"","folderPath":"DB Flow/mohan/dc","workSchemaName":"Snowflake_WS_$_6_11_32_0_52","diagramSchema":null},"analysis":[],"datamodels":[],"tagDetails":[],"dataCompares":[]}