{"pipelineKey":"3bcc309cccf34c479d12bc240c1ceb33","name":"azure start task frompipeline","description":"","definition":"{\"tasks\":[{\"parent\":[\"Terminator\"],\"livyServer\":\"${AzureStart}\",\"children\":[\"DatabricksLIF37\"],\"iteratee\":{},\"name\":\"AzureStart\",\"stackName\":\"azureenvfromclustersscreen\",\"action\":\"start\",\"id\":\"DatabricksGalUG\",\"label\":\"AzureCluster\",\"clusterId\":\"0125-112252-2y5h7igj\",\"type\":\"AzureCluster\",\"userId\":\"101\"},{\"parent\":[\"DatabricksGalUG\"],\"livyServer\":\"${AzureStart}\",\"children\":[],\"iteratee\":{},\"name\":\"AzureStop\",\"action\":\"stop\",\"id\":\"DatabricksLIF37\",\"label\":\"AzureCluster\",\"type\":\"AzureCluster\",\"userId\":\"101\"},{\"children\":[\"DatabricksGalUG\"],\"iteratee\":{},\"id\":\"Terminator\",\"type\":\"Terminator\"}]}"}