{"pipelineKey":"23dfae7c6aa147a48d1cd1285758c8e9","name":"azure create task 25","description":"","definition":"{\"tasks\":[{\"parent\":[\"Terminator\"],\"livyServer\":\"${AzureStart}\",\"children\":[\"DatabricksTBkU6\"],\"iteratee\":{},\"name\":\"AzureStart\",\"stackName\":\"azureenvcreatetask\",\"action\":\"create\",\"id\":\"Databricksmoxbf\",\"label\":\"AzureCluster\",\"type\":\"AzureCluster\",\"templateId\":\"32\",\"userId\":\"101\"},{\"parent\":[\"Databricksmoxbf\"],\"livyServer\":\"${AzureStart}\",\"children\":[],\"iteratee\":{},\"name\":\"AzureStop\",\"action\":\"stop\",\"id\":\"DatabricksTBkU6\",\"label\":\"AzureCluster\",\"type\":\"AzureCluster\",\"userId\":\"101\"},{\"children\":[\"Databricksmoxbf\"],\"iteratee\":{},\"id\":\"Terminator\",\"type\":\"Terminator\"}]}"}