{"pipelineKey":"00a7e3e830ec4c06839082a34e3fe063","name":"br055","description":"stopfailure","definition":"{\"tasks\":[{\"parent\":[\"DataflowV70hA\"],\"stopOnTaskFailure\":\"N\",\"dfName\":\"p1\",\"label\":\"Data\",\"type\":\"runDataFlow\",\"userId\":\"2\",\"dfKey\":\"d4506c9c-8701-497e-948d-d65143676eac\",\"livyServer\":\"${AzureStart}\",\"children\":[\"DataflowvXRWW\"],\"iteratee\":{},\"name\":\"p1\",\"id\":\"DataflowOWNOJ\",\"parameters\":\"limit_rows:limit 1000\"},{\"parent\":[\"DatabricksQTT4B\"],\"stopOnTaskFailure\":\"Y\",\"dfName\":\"datacompare\",\"label\":\"Data\",\"type\":\"runDataFlow\",\"userId\":\"2\",\"dfKey\":\"f9583989-fdba-4dab-9d8c-f2a3bc88ea9d\",\"livyServer\":\"${AzureStart}\",\"children\":[\"DataflowCQe2O\"],\"iteratee\":{},\"name\":\"datacompare\",\"id\":\"DataflowXLpqu\",\"parameters\":\"limit_rows:limit 1000\"},{\"parent\":[\"DataflowvXRWW\"],\"stopOnTaskFailure\":\"N\",\"dfName\":\"p2_Copy\",\"label\":\"Data\",\"type\":\"runDataFlow\",\"userId\":\"2\",\"dfKey\":\"4399370f-346f-44a2-96bd-bbfd6cc892e4\",\"livyServer\":\"${AzureStart}\",\"children\":[\"DatabricksMD6xb\"],\"iteratee\":{},\"name\":\"p2_Copy\",\"id\":\"DataflowLJncr\",\"parameters\":\"limit_rows:limit 1000\"},{\"parent\":[\"Terminator\"],\"livyServer\":\"$AzureStart\",\"children\":[\"DataflowXLpqu\"],\"iteratee\":{},\"name\":\"AzureStart\",\"stackName\":\"nov2 siri\",\"action\":\"start\",\"id\":\"DatabricksQTT4B\",\"label\":\"AzureCluster\",\"clusterId\":\"1102-161848-gvkpw93k\",\"type\":\"AzureCluster\",\"userId\":\"2\"},{\"children\":[\"DatabricksQTT4B\"],\"iteratee\":{},\"id\":\"Terminator\",\"type\":\"Terminator\"},{\"parent\":[\"DataflowLJncr\"],\"livyServer\":\"${AzureStart}\",\"children\":[],\"iteratee\":{},\"name\":\"AzureStop\",\"action\":\"stop\",\"id\":\"DatabricksMD6xb\",\"label\":\"AzureCluster\",\"type\":\"AzureCluster\",\"userId\":\"2\"},{\"parent\":[\"DataflowOWNOJ\"],\"stopOnTaskFailure\":\"N\",\"dfName\":\"p2\",\"label\":\"Data\",\"type\":\"runDataFlow\",\"userId\":\"2\",\"dfKey\":\"b1f7e3b2-cd9c-46c9-b986-9ad02d63a4c8\",\"livyServer\":\"${AzureStart}\",\"children\":[\"DataflowLJncr\"],\"iteratee\":{},\"name\":\"p2\",\"id\":\"DataflowvXRWW\",\"parameters\":\"limit_rows:limit 1000\"}]}"}