{"pipelineKey":"7a01d9c7f575433bb24dc249b92f0d0a","name":"Pipeline_2837","description":"","definition":"{\"workerLimit\":4,\"tasks\":[{\"parent\":[\"Terminator\"],\"children\":[\"EMRRPTCg\"],\"iteratee\":{},\"name\":\"EMRStart\",\"stackName\":\"DGd\",\"action\":\"start\",\"appendDateToStackName\":\"Y\",\"id\":\"EMRFlXBO\",\"label\":\"Emr\",\"type\":\"EMR\",\"templateId\":\"22\",\"userId\":\"18\"},{\"parent\":[\"EMRFlXBO\"],\"children\":[],\"iteratee\":{},\"name\":\"EMRStop\",\"stackName\":\"${EMRStart}\",\"action\":\"stop\",\"id\":\"EMRRPTCg\",\"label\":\"Emr\",\"type\":\"EMR\",\"templateId\":\"\",\"userId\":\"18\"},{\"children\":[\"EMRFlXBO\"],\"iteratee\":{},\"id\":\"Terminator\",\"type\":\"Terminator\"}]}"}