{"pipelineKey":"9a7f2240-278a-443a-b858-fceed2c07139","name":"Pipeline_env","description":"","definition":"{\"workerLimit\":4,\"tasks\":[{\"parent\":[\"Terminator\"],\"stopOnTaskFailure\":\"N\",\"dfName\":\"Dataflow_env\",\"stopDependentTasks\":\"N\",\"label\":\"Data\",\"type\":\"runDataFlow\",\"dfKey\":\"82e77fd1-b9be-4c68-b55b-63b2811aeca3\",\"children\":[],\"environmentName\":\"${environmentName}\",\"iteratee\":{},\"name\":\"Dataflow_env\",\"id\":\"DataflowK3h91\",\"parameters\":\"limit_rows:limit 1000\"},{\"children\":[\"DataflowK3h91\"],\"iteratee\":{},\"id\":\"Terminator\",\"type\":\"Terminator\"}]}"}