{"dataflow":{"dfKey":"7259c7f3-f034-419c-b24c-4cfb59ed24db","name":"DB_FLOW_20231219202920_CHILD_TABLE","tags":null,"description":"","definition":"{\"name\":\"DB_FLOW_20231219202920_CHILD_TABLE\",\"description\":\"\",\"components\":[{\"query\":\"select ID,ORDERID,ORDERNUMBER from SH.CHILD_TABLE\",\"partitionOptions\":{\"partitionType\":\"\",\"name\":\"\"},\"enableTrim\":\"N\",\"easyQueryDefJson\":{\"sqlQuery\":\"\"},\"componentId\":1,\"componentName\":\"src_CHILD_TABLE\",\"tableName\":\"src_CHILD_TABLE\",\"category\":\"Source\",\"componentType\":\"TestCase JDBC\",\"rank\":0,\"dataSourceName\":\"Oracle_ora\",\"displayRows\":50,\"dependencies\":[],\"className\":\"com.datagaps.dataflow.models.JDBCComponent\",\"executionOption\":\"allparentpassorfail\",\"excludeNotification\":\"N\"},{\"query\":\"select ID,ORDERID,ORDERNUMBER from SH.CHILD_TABLE\",\"partitionOptions\":{\"partitionType\":\"\",\"name\":\"\"},\"enableTrim\":\"N\",\"easyQueryDefJson\":{\"sqlQuery\":\"\"},\"componentId\":2,\"componentName\":\"tgt_CHILD_TABLE\",\"tableName\":\"tgt_CHILD_TABLE\",\"category\":\"Source\",\"componentType\":\"TestCase JDBC\",\"rank\":0,\"dataSourceName\":\"Oracle_ora\",\"displayRows\":50,\"dependencies\":[],\"className\":\"com.datagaps.dataflow.models.JDBCComponent\",\"executionOption\":\"allparentpassorfail\",\"excludeNotification\":\"N\"},{\"sourceDataFrame\":\"src_CHILD_TABLE\",\"targetDataFrame\":\"tgt_CHILD_TABLE\",\"mapping\":[{\"sourceColumn\":\"ID\",\"sourceType\":\"NUMBER\",\"targetColumn\":\"ID\",\"targetType\":\"NUMBER\",\"unique\":\"N\",\"sourceDataFormat\":\"\",\"targetDataFormat\":\"\",\"sourceTypeChange\":\"N\",\"targetTypeChange\":\"N\",\"originalSourceType\":\"NUMBER\",\"orginalTargetType\":\"NUMBER\",\"columnOrder\":0},{\"sourceColumn\":\"ORDERID\",\"sourceType\":\"NUMBER\",\"targetColumn\":\"ORDERID\",\"targetType\":\"NUMBER\",\"unique\":\"Y\",\"sourceDataFormat\":\"\",\"targetDataFormat\":\"\",\"sourceTypeChange\":\"N\",\"targetTypeChange\":\"N\",\"originalSourceType\":\"NUMBER\",\"orginalTargetType\":\"NUMBER\",\"columnOrder\":1},{\"sourceColumn\":\"ORDERNUMBER\",\"sourceType\":\"NUMBER\",\"targetColumn\":\"ORDERNUMBER\",\"targetType\":\"NUMBER\",\"unique\":\"N\",\"sourceDataFormat\":\"\",\"targetDataFormat\":\"\",\"sourceTypeChange\":\"N\",\"targetTypeChange\":\"N\",\"originalSourceType\":\"NUMBER\",\"orginalTargetType\":\"NUMBER\",\"columnOrder\":2}],\"onlyInA\":\"Y\",\"onlyInB\":\"Y\",\"difference\":\"Y\",\"enableTrim\":\"N\",\"replaceNull\":\"N\",\"autoDataTypeConversion\":\"N\",\"columnDifferencesCount\":\"N\",\"ignoreCase\":\"N\",\"hasDuplicates\":\"N\",\"subDataFrames\":[{\"subDataFrameName\":\"_Matched\",\"type\":\"Matched\"},{\"subDataFrameName\":\"_Source_Duplicate\",\"type\":\"Duplicates In A\"},{\"subDataFrameName\":\"_Target_Duplicate\",\"type\":\"Duplicates In B\"},{\"subDataFrameName\":\"_Difference\",\"type\":\"Difference\"},{\"subDataFrameName\":\"_OnlySource\",\"type\":\"Only In A\"},{\"subDataFrameName\":\"_OnlyTarget\",\"type\":\"Only In B\"}],\"onlyInAThresholdUnit\":\"number\",\"onlyInAThreshold\":0.0,\"onlyInBThresholdUnit\":\"number\",\"onlyInBThreshold\":0.0,\"differencesSourceThresholdUnit\":\"number\",\"differencesSourceThreshold\":0.0,\"differencesTargetThresholdUnit\":\"number\",\"differencesTargetThreshold\":0.0,\"componentId\":3,\"componentName\":\"dc_CHILD_TABLE\",\"tableName\":\"dc_CHILD_TABLE_3RNt\",\"category\":\"Data Quality\",\"componentType\":\"TestCase DataCompare\",\"rank\":0,\"dataSourceName\":\"\",\"displayRows\":50,\"dependencies\":[1,2],\"options\":{},\"className\":\"com.datagaps.dataflow.models.DataCompareComponent\",\"executionOption\":\"allparentpassorfail\",\"excludeNotification\":\"N\"}],\"isDeleteWorkSchemaTable\":\"N\"}","parameters":"[{\"name\":\"limit_rows\",\"defValueInInteractiveMode\":\"limit 1000\",\"defValueInBatchMode\":\"limit 10\"}]","version":3,"maxComponentId":3,"livyOptions":null,"isDeleted":"N","userName":null,"type":"componenttestcase","environmentName":null,"folderPath":"DB Flow/1000dbfs","workSchemaName":"PostgreSQL_Workschema"},"analysis":[],"datamodels":[],"tagDetails":[],"dataCompares":[]}