{"dataflow":{"dfKey":"5744d8cd-5029-403d-8d02-257ac9bbbec6","name":"Dataflow_3452","tags":null,"description":null,"definition":"{\"name\":\"Dataflow_3452\",\"engineVariableName\":\"\",\"components\":[{\"udfNames\":[],\"componentId\":0,\"componentName\":\"startComponent\",\"tableName\":\"\",\"category\":\"Start\",\"componentType\":\"UDF\",\"rank\":0,\"dataSourceName\":\"\",\"displayRows\":0,\"dependencies\":[],\"className\":\"com.datagaps.dataflow.models.UDFComponent\",\"executionOption\":\"\",\"excludeNotification\":\"Y\"},{\"format\":\"csv\",\"enableSchema\":\"N\",\"schema\":[],\"fileMetadata\":[],\"enableTrim\":\"N\",\"componentId\":1,\"componentName\":\"File 1\",\"tableName\":\"File_1\",\"category\":\"Source\",\"componentType\":\"File\",\"rank\":0,\"dataSourceName\":\"CSVs3manoj\",\"displayRows\":50,\"dependencies\":[],\"options\":{\"delimiter\":\",\",\"header\":\"true\",\"inferSchema\":\"true\",\"path\":\"Customers.csv\"},\"className\":\"com.datagaps.dataflow.models.FileComponent\",\"isCheckpointEnabled\":\"N\",\"dataSourceLogicalName\":\"\",\"executionOption\":\"\",\"excludeNotification\":\"N\"},{\"enableTrim\":\"N\",\"componentId\":2,\"componentName\":\"Generic 2\",\"tableName\":\"Generic_2\",\"category\":\"Source\",\"componentType\":\"Generic\",\"rank\":0,\"dataSourceName\":\"Oracle\",\"displayRows\":50,\"dependencies\":[1],\"options\":{\"dbTable\":\"select * from customers\"},\"className\":\"com.datagaps.dataflow.models.GenericComponent\",\"isCheckpointEnabled\":\"N\",\"dataSourceLogicalName\":\"\",\"executionOption\":\"allparentpassorfail\",\"excludeNotification\":\"N\"},{\"sourceDataFrame\":\"File_1\",\"profileOptions\":{\"rowCount\":\"Y\",\"nulls\":\"Y\",\"nullCount\":\"Y\",\"distinctPercentage\":\"Y\",\"distinctCount\":\"Y\",\"minValue\":\"Y\",\"maxValue\":\"Y\",\"constancy\":\"Y\",\"minLength\":\"Y\",\"maxLength\":\"Y\",\"mean\":\"Y\",\"maxDecimalCount\":\"Y\",\"kurtosis\":\"Y\",\"skewness\":\"Y\",\"sum\":\"Y\",\"stddev\":\"Y\",\"frequencyAnalysis\":\"Y\",\"patternAnalysis\":\"Y\"},\"profileColumns\":[{\"columnName\":\"CustomerKey\",\"dataType\":\"integer\",\"profile\":\"Yes\"},{\"columnName\":\"GeographyKey\",\"dataType\":\"integer\",\"profile\":\"Yes\"},{\"columnName\":\"CustomerAlternateKey\",\"dataType\":\"string\",\"profile\":\"Yes\"},{\"columnName\":\"Title\",\"dataType\":\"string\",\"profile\":\"Yes\"},{\"columnName\":\"Name\",\"dataType\":\"string\",\"profile\":\"Yes\"},{\"columnName\":\"NameStyle\",\"dataType\":\"boolean\",\"profile\":\"Yes\"},{\"columnName\":\"BirthDate\",\"dataType\":\"string\",\"profile\":\"Yes\"},{\"columnName\":\"MaritalStatus\",\"dataType\":\"string\",\"profile\":\"Yes\"},{\"columnName\":\"Suffix\",\"dataType\":\"string\",\"profile\":\"Yes\"},{\"columnName\":\"Gender\",\"dataType\":\"string\",\"profile\":\"Yes\"},{\"columnName\":\"EmailAddress\",\"dataType\":\"string\",\"profile\":\"Yes\"},{\"columnName\":\"YearlyIncome\",\"dataType\":\"integer\",\"profile\":\"Yes\"},{\"columnName\":\"TotalChildren\",\"dataType\":\"integer\",\"profile\":\"Yes\"},{\"columnName\":\"NumberChildrenAtHome\",\"dataType\":\"integer\",\"profile\":\"Yes\"},{\"columnName\":\"EnglishEducation\",\"dataType\":\"string\",\"profile\":\"Yes\"},{\"columnName\":\"SpanishEducation\",\"dataType\":\"string\",\"profile\":\"Yes\"},{\"columnName\":\"FrenchEducation\",\"dataType\":\"string\",\"profile\":\"Yes\"},{\"columnName\":\"EnglishOccupation\",\"dataType\":\"string\",\"profile\":\"Yes\"},{\"columnName\":\"SpanishOccupation\",\"dataType\":\"string\",\"profile\":\"Yes\"},{\"columnName\":\"FrenchOccupation\",\"dataType\":\"string\",\"profile\":\"Yes\"},{\"columnName\":\"HouseOwnerFlag\",\"dataType\":\"integer\",\"profile\":\"Yes\"},{\"columnName\":\"NumberCarsOwned\",\"dataType\":\"integer\",\"profile\":\"Yes\"},{\"columnName\":\"AddressLine1\",\"dataType\":\"string\",\"profile\":\"Yes\"},{\"columnName\":\"AddressLine2\",\"dataType\":\"string\",\"profile\":\"Yes\"},{\"columnName\":\"Phone\",\"dataType\":\"string\",\"profile\":\"Yes\"},{\"columnName\":\"DateFirstPurchase\",\"dataType\":\"string\",\"profile\":\"Yes\"},{\"columnName\":\"CommuteDistance\",\"dataType\":\"string\",\"profile\":\"Yes\"}],\"sampleSize\":100,\"profilePrediction\":{\"predictionType\":\"stddev\",\"details\":\"{\\\"minimumDataPoints\\\":3,\\\"rollingWindow\\\":3,\\\"standardDeviationValue\\\":3}\"},\"oberservabilities\":[\"rowCount\",\"nulls\",\"mean\",\"distinctPercentage\"],\"failComponentWhenDatasetEmpty\":\"N\",\"componentId\":3,\"componentName\":\"Data Profile 3\",\"tableName\":\"Data_Profile_3\",\"category\":\"Data Quality\",\"componentType\":\"Data Profile\",\"rank\":0,\"displayRows\":50,\"dependencies\":[2,1],\"className\":\"com.datagaps.dataflow.models.ProfileComponent\",\"isCheckpointEnabled\":\"N\",\"executionOption\":\"allparentpassorfail\",\"excludeNotification\":\"N\"},{\"dataframes\":[{\"dataframeId\":1,\"sourceDataFrame\":\"Generic_2\",\"targetDataSourceId\":10599,\"writeOptions\":{\"delimiter\":\",\",\"header\":\"true\"},\"name\":\"Target File 1\",\"targetType\":\"File\",\"format\":\"CSV\",\"isChecked\":true,\"runId\":0,\"columns\":[],\"partitionOptions\":{\"partitionType\":\"\",\"name\":\"\"},\"subfolderType\":\"Static\",\"subfolderName\":\"Target4_TargetFile1\",\"nameOption\":\"\",\"sqlExpression\":\"\",\"saveMode\":\"append\",\"dataSourceLogicalName\":\"\"},{\"dataframeId\":2,\"sourceDataFrame\":\"File_1\",\"targetDataSourceId\":10599,\"writeOptions\":{\"delimiter\":\",\",\"header\":\"true\"},\"name\":\"Target File 2\",\"targetType\":\"File\",\"format\":\"CSV\",\"isChecked\":true,\"runId\":0,\"columns\":[],\"partitionOptions\":{\"partitionType\":\"\",\"name\":\"\"},\"subfolderType\":\"Static\",\"subfolderName\":\"Target4_TargetFile2\",\"nameOption\":\"\",\"sqlExpression\":\"\",\"saveMode\":\"append\",\"dataSourceLogicalName\":\"\"}],\"componentId\":4,\"componentName\":\"Target 4\",\"tableName\":\"\",\"category\":\"Sink\",\"componentType\":\"Target\",\"rank\":0,\"dataSourceName\":\"\",\"displayRows\":50,\"dependencies\":[3,1,2],\"className\":\"com.datagaps.dataflow.models.SyncComponent\",\"executionOption\":\"allparentpassorfail\",\"excludeNotification\":\"N\"},{\"metricsCompareMappings\":[{\"mappingName\":\"ACCOUNTS to ACCOUNTS comparison\",\"sourceQuery\":\"select count(*) from SH.ACCOUNTS\",\"targetQuery\":\"select count(*) from SH.ACCOUNTS\",\"severity\":\"None\",\"comparisionThreshold\":{\"thresholdType\":\"#\",\"upperValue\":0.0,\"lowerValue\":0.0}},{\"mappingName\":\"ACTORAUTOMATION to ACTORAUTOMATION comparison\",\"sourceQuery\":\"select count(*) from SH.ACTORAUTOMATION\",\"targetQuery\":\"select count(*) from SH.ACTORAUTOMATION\",\"severity\":\"None\",\"comparisionThreshold\":{\"thresholdType\":\"#\",\"upperValue\":0.0,\"lowerValue\":0.0}}],\"sourceDatasourceName\":\"Oracle\",\"targetDatasourceName\":\"Oracle\",\"parallelThreads\":5,\"sourceDatasourceLogicalName\":\"\",\"targetDatasourceLogicalName\":\"\",\"componentId\":5,\"componentName\":\"Metrics Compare 5\",\"tableName\":\"Metrics_Compare_5\",\"category\":\"Data Quality\",\"componentType\":\"METRICS COMPARE\",\"rank\":0,\"displayRows\":0,\"dependencies\":[4],\"className\":\"com.datagaps.dataflow.models.MetricsCompareComponent\",\"executionOption\":\"allparentpassorfail\",\"excludeNotification\":\"N\"},{\"dataframes\":[{\"dataframeId\":1,\"sourceDataFrame\":\"File_1\",\"targetDataSourceId\":10599,\"writeOptions\":{\"delimiter\":\",\",\"header\":\"true\"},\"name\":\"Target File 1\",\"targetType\":\"File\",\"format\":\"CSV\",\"isChecked\":true,\"runId\":0,\"columns\":[],\"partitionOptions\":{\"partitionType\":\"\",\"name\":\"\"},\"subfolderType\":\"Static\",\"subfolderName\":\"Target6_TargetFile1\",\"nameOption\":\"\",\"sqlExpression\":\"\",\"saveMode\":\"append\",\"dataSourceLogicalName\":\"\"}],\"componentId\":6,\"componentName\":\"Target 6\",\"tableName\":\"\",\"category\":\"Sink\",\"componentType\":\"Target\",\"rank\":0,\"dataSourceName\":\"\",\"displayRows\":50,\"dependencies\":[5,1],\"className\":\"com.datagaps.dataflow.models.SyncComponent\",\"executionOption\":\"allparentpassorfail\",\"excludeNotification\":\"N\"}],\"isDeleteWorkSchemaTable\":\"N\"}","parameters":"[{\"name\":\"limit_rows\",\"defValueInInteractiveMode\":\"limit 10\",\"defValueInBatchMode\":\"limit 1000\"}]","version":3,"maxComponentId":6,"livyOptions":null,"isDeleted":"N","userName":null,"type":"dataflow","environmentName":"","folderPath":"Dataflow/GITTESTSIRI","workSchemaName":null},"analysis":[],"datamodels":[],"tagDetails":[],"dataCompares":[]}