{"dataflow":{"dfKey":"50a1f6b2-016b-45d0-8bbe-a4066496309f","name":"DB_FLOW_20240328151905_CUSTOMERSWS","tags":null,"description":"","definition":"{\"name\":\"DB_FLOW_20240328151905_CUSTOMERSWS\",\"description\":\"\",\"components\":[{\"query\":\"select CUST_FIRST_NAME,CUST_ID from HR.CUSTOMERSWS\",\"partitionOptions\":{\"partitionType\":\"\",\"name\":\"\"},\"enableTrim\":\"N\",\"easyQueryDefJson\":{\"sqlQuery\":\"\"},\"componentId\":1,\"componentName\":\"src_CUSTOMERSWS\",\"tableName\":\"src_CUSTOMERSWS_OB4s\",\"category\":\"Source\",\"componentType\":\"TestCase JDBC\",\"rank\":0,\"dataSourceName\":\"Oracle_102\",\"displayRows\":50,\"dependencies\":[],\"className\":\"com.datagaps.dataflow.models.JDBCComponent\",\"executionOption\":\"allparentpassorfail\",\"excludeNotification\":\"N\"},{\"query\":\"select CUST_FIRST_NAME,CUST_ID from HR.CUSTOMERSWS\",\"partitionOptions\":{\"partitionType\":\"\",\"name\":\"\"},\"enableTrim\":\"N\",\"easyQueryDefJson\":{\"sqlQuery\":\"\"},\"componentId\":2,\"componentName\":\"tgt_CUSTOMERSWS\",\"tableName\":\"tgt_CUSTOMERSWS_UV4J\",\"category\":\"Source\",\"componentType\":\"TestCase JDBC\",\"rank\":0,\"dataSourceName\":\"Oracle_102\",\"displayRows\":50,\"dependencies\":[],\"className\":\"com.datagaps.dataflow.models.JDBCComponent\",\"executionOption\":\"allparentpassorfail\",\"excludeNotification\":\"N\"},{\"sourceDataFrame\":\"src_CUSTOMERSWS_OB4s\",\"targetDataFrame\":\"tgt_CUSTOMERSWS_UV4J\",\"mapping\":[{\"sourceColumn\":\"CUST_FIRST_NAME\",\"sourceType\":\"VARCHAR2\",\"targetColumn\":\"CUST_FIRST_NAME\",\"targetType\":\"VARCHAR2\",\"unique\":\"N\",\"sourceDataFormat\":\"\",\"targetDataFormat\":\"\",\"sourceTypeChange\":\"N\",\"targetTypeChange\":\"N\",\"originalSourceType\":\"VARCHAR2\",\"orginalTargetType\":\"VARCHAR2\",\"columnOrder\":0},{\"sourceColumn\":\"CUST_ID\",\"sourceType\":\"NUMBER\",\"targetColumn\":\"CUST_ID\",\"targetType\":\"NUMBER\",\"unique\":\"N\",\"sourceDataFormat\":\"\",\"targetDataFormat\":\"\",\"sourceTypeChange\":\"N\",\"targetTypeChange\":\"N\",\"originalSourceType\":\"NUMBER\",\"orginalTargetType\":\"NUMBER\",\"columnOrder\":1}],\"onlyInA\":\"Y\",\"onlyInB\":\"Y\",\"difference\":\"Y\",\"enableTrim\":\"N\",\"replaceNull\":\"N\",\"autoDataTypeConversion\":\"N\",\"columnDifferencesCount\":\"N\",\"ignoreCase\":\"N\",\"hasDuplicates\":\"N\",\"subDataFrames\":[{\"subDataFrameName\":\"_Matched\",\"type\":\"Matched\"},{\"subDataFrameName\":\"_Source_Duplicate\",\"type\":\"Duplicates In A\"},{\"subDataFrameName\":\"_Target_Duplicate\",\"type\":\"Duplicates In B\"},{\"subDataFrameName\":\"_Difference\",\"type\":\"Difference\"},{\"subDataFrameName\":\"_OnlySource\",\"type\":\"Only In A\"},{\"subDataFrameName\":\"_OnlyTarget\",\"type\":\"Only In B\"}],\"onlyInAThresholdUnit\":\"number\",\"onlyInAThreshold\":0.0,\"onlyInBThresholdUnit\":\"number\",\"onlyInBThreshold\":0.0,\"differencesSourceThresholdUnit\":\"number\",\"differencesSourceThreshold\":0.0,\"differencesTargetThresholdUnit\":\"number\",\"differencesTargetThreshold\":0.0,\"componentId\":3,\"componentName\":\"dc_CUSTOMERSWS\",\"tableName\":\"dc_CUSTOMERSWS_JoYv\",\"category\":\"Data Reconciliation\",\"componentType\":\"TestCase DataCompare\",\"rank\":0,\"dataSourceName\":\"\",\"displayRows\":50,\"dependencies\":[1,2],\"options\":{},\"className\":\"com.datagaps.dataflow.models.DataCompareComponent\",\"executionOption\":\"allparentpassorfail\",\"excludeNotification\":\"N\"}],\"isDeleteWorkSchemaTable\":\"N\"}","parameters":"[{\"name\":\"limit_rows\",\"defValueInInteractiveMode\":\"limit 1000\",\"defValueInBatchMode\":\"limit 10\"}]","version":3,"maxComponentId":3,"livyOptions":null,"isDeleted":"N","userName":null,"type":"componenttestcase","environmentName":null,"folderPath":"DB Flow/301dbflows","workSchemaName":"PostgreSQL_Workschema"},"analysis":[],"datamodels":[],"tagDetails":[],"dataCompares":[]}